aind_spurious_correlation/__init__.py
aind_spurious_correlation/methods.py
aind_spurious_correlation-0.0.6.dist-info/licenses/LICENSE
aind_spurious_correlation-0.0.6.dist-info/METADATA
aind_spurious_correlation-0.0.6.dist-info/WHEEL
aind_spurious_correlation-0.0.6.dist-info/top_level.txt
aind_spurious_correlation-0.0.6.dist-info/RECORD
